robo_gestor/__init__.py
robo_gestor/robo_gestor.py
robo_gestor-0.1.1.dist-info/METADATA
robo_gestor-0.1.1.dist-info/WHEEL
robo_gestor-0.1.1.dist-info/top_level.txt
robo_gestor-0.1.1.dist-info/RECORD
