Metadata-Version: 2.4
Name: robo-gestor
Version: 0.1.1
Summary: A Python automation utility for interacting with Android devices via uiautomator2.
Home-page: https://github.com/RohitKumarGit/RoboGestor
Author: Rohit Kumar
Author-email: mailrohitkr6@gmail.com
Classifier: Programming Language :: Python :: 3
Classifier: License :: OSI Approved :: MIT License
Classifier: Operating System :: OS Independent
Requires-Python: >=3.6
Requires-Dist: uiautomator2
Dynamic: author
Dynamic: author-email
Dynamic: classifier
Dynamic: description
Dynamic: description-content-type
Dynamic: home-page
Dynamic: requires-dist
Dynamic: requires-python
Dynamic: summary
